mergedownloader/__init__.py
mergedownloader/cli.py
mergedownloader/downloader.py
mergedownloader/enums.py
mergedownloader/inpeparser.py
mergedownloader/parser.py
mergedownloader/utils.py
merge_downloader-0.0.3.dist-info/LICENSE
merge_downloader-0.0.3.dist-info/METADATA
merge_downloader-0.0.3.dist-info/WHEEL
merge_downloader-0.0.3.dist-info/entry_points.txt
merge_downloader-0.0.3.dist-info/top_level.txt
merge_downloader-0.0.3.dist-info/RECORD
